{
  "generated_at_utc": "2026-04-30T03:01:04Z",
  "as_of": {
    "price_date": "2026-04-29",
    "run_time_utc": "2026-04-30 03:01:04"
  },
  "data_warning": false,
  "warnings": [],
  "thresholds": {
    "RISK": {
      "VIX_MAX": 30.0,
      "HY_4W_CHG_BP_MAX": 150.0,
      "IG_4W_CHG_BP_MAX": 80.0,
      "REALYIELD_4W_CHG_BP_MAX": 50.0,
      "NFCI_MAX": 0.5
    },
    "REGIME": {
      "MINERS_RS_GAP_MIN": 0.0,
      "MINERS_RS_SLOPE_MIN": 0.0,
      "METALS_MA_SLOPE_LOOKBACK": 20.0
    },
    "VZLA": {
      "ATR14_PCT_MAX": 0.15,
      "GAP_OPEN_MAX": 0.08,
      "SHOCK_DOWN_RET": -0.12,
      "SHOCK_DOWN_VOL": 2.0,
      "SHOCK_UP_RET": 0.25,
      "SHOCK_UP_VOL": 3.0,
      "PULLBACK_GAP20_MIN": -0.02,
      "PULLBACK_GAP20_MAX": 0.05,
      "PULLBACK_RSI_MIN": 40.0,
      "PULLBACK_RSI_MAX": 60.0,
      "BREAKOUT_WIN": 60.0,
      "BREAKOUT_BUFFER": 1.01,
      "BREAKOUT_VOL_MIN": 2.0,
      "BREAKOUT_RSI_MIN": 60.0,
      "RS_GAP_MIN": 0.0,
      "RS_SLOPE_MIN": 0.0,
      "GAP20_OVERHEAT_MAX": 0.15
    },
    "SCZM": {
      "SILVER_WATCH": 32.0,
      "SILVER_ENTRY": 35.0,
      "ATR14_PCT_MAX": 0.2,
      "GAP_OPEN_MAX": 0.1,
      "SHOCK_DOWN_RET": -0.12,
      "SHOCK_DOWN_VOL": 2.0,
      "PULLBACK_GAP20_MIN": -0.02,
      "PULLBACK_GAP20_MAX": 0.07,
      "PULLBACK_RSI_MIN": 35.0,
      "PULLBACK_RSI_MAX": 60.0,
      "PULLBACK_VOL_MIN": 1.2,
      "BREAKOUT_WIN": 40.0,
      "BREAKOUT_BUFFER": 1.01,
      "BREAKOUT_VOL_MIN": 1.5,
      "BREAKOUT_RSI_MIN": 55.0,
      "RS_GAP_MIN": 0.0,
      "RS_SLOPE_MIN": 0.0,
      "GAP20_OVERHEAT_MAX": 0.18
    },
    "HYMC": {
      "ATR14_PCT_MAX": 0.25,
      "GAP_OPEN_MAX": 0.12,
      "SHOCK_DOWN_RET": -0.15,
      "SHOCK_DOWN_VOL": 2.5,
      "SHOCK_UP_RET": 0.3,
      "SHOCK_UP_VOL": 4.0,
      "BREAKOUT_WIN": 120.0,
      "BREAKOUT_BUFFER": 1.01,
      "BREAKOUT_VOL_MIN": 2.0,
      "BREAKOUT_VOL_MAX": 8.0,
      "BREAKOUT_RSI_MIN": 55.0,
      "RETEST_GAP50_MAX": 0.05,
      "RETEST_RSI_MIN": 50.0,
      "RS_GAP_MIN": 0.0,
      "RS_SLOPE_MIN": 0.0,
      "GAP20_OVERHEAT_MAX": 0.2
    }
  },
  "macro": {
    "BAMLH0A0HYM2": {
      "latest": 2.85,
      "change_4w": -43.0,
      "latest_date": "2026-04-28"
    },
    "BAMLC0A0CM": {
      "latest": 0.81,
      "change_4w": -9.0,
      "latest_date": "2026-04-28"
    },
    "DFII10": {
      "latest": 1.92,
      "change_4w": -8.0,
      "latest_date": "2026-04-28"
    },
    "VIXCLS": {
      "latest": 17.83,
      "change_4w": -7.42,
      "latest_date": "2026-04-28"
    },
    "NFCI": {
      "latest": -0.518,
      "change_4w": -0.059,
      "latest_date": "2026-04-24"
    }
  },
  "risk_checks": {
    "VIX_lt_max": true,
    "HY_4w_chg_bp_lt_max": true,
    "IG_4w_chg_bp_lt_max": true,
    "RealYield_4w_chg_bp_lt_max": true,
    "NFCI_lte_max": true
  },
  "prices": {
    "VZLA": {
      "close": 3.4,
      "latest_date": "2026-04-29"
    },
    "SCZM": {
      "close": 7.73,
      "latest_date": "2026-04-29"
    },
    "HYMC": {
      "close": 34.209999,
      "latest_date": "2026-04-29"
    },
    "SI=F": {
      "close": 72.745003,
      "latest_date": "2026-04-29"
    },
    "GC=F": {
      "close": 4575.399902,
      "latest_date": "2026-04-29"
    },
    "SILJ": {
      "close": 28.35,
      "latest_date": "2026-04-29"
    },
    "SLV": {
      "close": 64.839996,
      "latest_date": "2026-04-29"
    },
    "GDXJ": {
      "close": 113.519997,
      "latest_date": "2026-04-29"
    },
    "GLD": {
      "close": 417.410004,
      "latest_date": "2026-04-29"
    }
  },
  "regime": {
    "risk_green": true,
    "silver_uptrend": false,
    "gold_uptrend": false,
    "miners_leadership": false,
    "junior_gold_leadership": false,
    "SILJ_over_SLV": {
      "ratio": 0.43723,
      "ma60": 0.453987,
      "gap": -0.036911,
      "ma60_slope_proxy": 0.015199
    },
    "GDXJ_over_GLD": {
      "ratio": 0.271963,
      "ma60": 0.287585,
      "gap": -0.054323,
      "ma60_slope_proxy": -0.00371
    },
    "metals": {
      "SI": {
        "close": 72.745003,
        "ma20": 76.13595,
        "ma50": 78.35978,
        "ma120": 74.005175,
        "ma200": 61.43143,
        "gap20": -0.044538,
        "gap50": -0.071654,
        "gap200": 0.184166,
        "ma50_slope20": -5.13538,
        "ma200_slope20": 3.951565,
        "rsi14": 42.667729,
        "atr14": 2.912802,
        "atr14_pct": 0.040041,
        "vol_ratio": 2.199126,
        "ret1d": -0.006284,
        "gap_open": 0.019739
      },
      "GC": {
        "close": 4575.399902,
        "ma20": 4728.48999,
        "ma50": 4848.11998,
        "ma120": 4630.773317,
        "ma200": 4241.771987,
        "gap20": -0.032376,
        "gap50": -0.056253,
        "gap200": 0.078653,
        "ma50_slope20": -92.284004,
        "ma200_slope20": 138.902999,
        "rsi14": 39.910574,
        "atr14": 93.7366,
        "atr14_pct": 0.020487,
        "vol_ratio": 9.208888,
        "ret1d": -0.003507,
        "gap_open": 0.007514
      }
    }
  },
  "signals": {
    "VZLA": {
      "name": "Vizsla Silver",
      "ta": {
        "close": 3.4,
        "ma20": 3.3685,
        "ma50": 3.57,
        "ma120": 4.477167,
        "ma200": 4.2068,
        "gap20": 0.009351,
        "gap50": -0.047619,
        "gap200": -0.191785,
        "ma50_slope20": -0.7306,
        "ma200_slope20": 0.0258,
        "rsi14": 48.114754,
        "atr14": 0.195237,
        "atr14_pct": 0.057423,
        "vol_ratio": 0.996473,
        "ret1d": -0.005848,
        "gap_open": 0.008772
      },
      "rs_vs_SILJ": {
        "ratio": 0.119929,
        "ma60": 0.113663,
        "gap": 0.05513,
        "ma60_slope_proxy": -0.023353
      },
      "checks": {
        "trend_ok": false,
        "rs_ok": false,
        "risk_ok": true,
        "shock_down": false,
        "shock_up": false,
        "pullback": true,
        "breakout": false
      },
      "entry_candidate": false,
      "entry_confirmed": false,
      "fails": [
        "SilverUptrend=FALSE",
        "MinersLeadership(SILJ/SLV)=FALSE",
        "Trend(MA200/MA50)=FALSE",
        "RelativeStrength(vs SILJ)=FALSE"
      ]
    },
    "SCZM": {
      "name": "Santacruz Silver",
      "ta": {
        "close": 7.73,
        "ma20": 8.4225,
        "ma50": 9.1882,
        "ma120": 9.355742,
        "ma200": 7.817329,
        "gap20": -0.08222,
        "gap50": -0.158704,
        "gap200": -0.011171,
        "ma50_slope20": -1.62373,
        "ma200_slope20": 0.532774,
        "rsi14": 40.224766,
        "atr14": 0.654422,
        "atr14_pct": 0.08466,
        "vol_ratio": 1.403874,
        "ret1d": -0.019036,
        "gap_open": 0.016497
      },
      "ma_long": 200,
      "silver_margin": {
        "SI_close": 72.745003,
        "watch_ge": 32.0,
        "entry_ge": 35.0,
        "watch": true,
        "entry": true
      },
      "rs_vs_SILJ": {
        "ratio": 0.272663,
        "ma60": 0.29181,
        "gap": -0.065614,
        "ma60_slope_proxy": -0.030942
      },
      "checks": {
        "trend_ok": false,
        "rs_ok": false,
        "risk_ok": true,
        "shock_down": false,
        "pullback": false,
        "breakout": false
      },
      "entry_candidate": false,
      "entry_confirmed": false,
      "fails": [
        "SilverUptrend=FALSE",
        "MinersLeadership(SILJ/SLV)=FALSE",
        "Trend(MA200/MA50)=FALSE",
        "RelativeStrength(vs SILJ)=FALSE",
        "Trigger(Pullback/Breakout)=FALSE"
      ]
    },
    "HYMC": {
      "name": "Hycroft Mining",
      "ta": {
        "close": 34.209999,
        "ma20": 38.56925,
        "ma50": 39.5666,
        "ma120": 30.43075,
        "ma200": 20.461725,
        "gap20": -0.113024,
        "gap50": -0.135382,
        "gap200": 0.671902,
        "ma50_slope20": -0.9199,
        "ma200_slope20": 3.5285,
        "rsi14": 41.406666,
        "atr14": 3.45242,
        "atr14_pct": 0.100918,
        "vol_ratio": 1.00229,
        "ret1d": -0.040662,
        "gap_open": 0.01318
      },
      "rs_vs_SILJ": {
        "ratio": 1.206702,
        "ma60": 1.203213,
        "gap": 0.0029,
        "ma60_slope_proxy": 0.040123
      },
      "rs_vs_GDXJ": {
        "ratio": 0.301357,
        "ma60": 0.302291,
        "gap": -0.003091,
        "ma60_slope_proxy": 0.006665
      },
      "checks": {
        "metals_ok": false,
        "sector_ok": false,
        "trend_ok": true,
        "rs_ok": true,
        "risk_ok": true,
        "shock_down": false,
        "shock_up": false,
        "breakout": false,
        "retest": false
      },
      "entry_candidate": false,
      "entry_confirmed": false,
      "fails": [
        "MetalsUptrend(SI&GC)=FALSE",
        "SectorLeadership(SILJ/SLV or GDXJ/GLD)=FALSE",
        "Trigger(Breakout/Retest)=FALSE"
      ]
    }
  },
  "verdict": "⏸ No entry today"
}