{
  "generated_at_utc": "2026-05-27T15:00:44Z",
  "as_of": {
    "price_date": "2026-05-27",
    "run_time_utc": "2026-05-27 15:00:44"
  },
  "data_warning": false,
  "warnings": [],
  "macro": {
    "BAMLH0A0HYM2": {
      "latest": 2.72,
      "change_4w_bp": -13.0,
      "latest_date": "2026-05-26"
    },
    "BAMLC0A0CM": {
      "latest": 0.74,
      "change_4w_bp": -7.0,
      "latest_date": "2026-05-26"
    },
    "DFII10": {
      "latest": 2.16,
      "change_4w_bp": 27.0,
      "latest_date": "2026-05-22"
    },
    "VIXCLS": {
      "latest": 17.01,
      "change_4w_bp": -82.0,
      "latest_date": "2026-05-26"
    },
    "NFCI": {
      "latest": -0.523,
      "change_4w_bp": -4.4,
      "latest_date": "2026-05-15"
    }
  },
  "checks": {
    "MacroGreen": true,
    "HY_4w_change_bp_lt_100": true,
    "IG_4w_change_bp_lt_50": true,
    "DFII10_4w_change_bp_lt_50": true,
    "VIX_lt_25": true,
    "NFCI_lte_0": true
  },
  "prices": {
    "VRT": {
      "close": 316.26,
      "latest_date": "2026-05-27"
    },
    "MRVL": {
      "close": 198.1901,
      "latest_date": "2026-05-27"
    },
    "SRVR": {
      "close": 34.665,
      "latest_date": "2026-05-27"
    },
    "SMH": {
      "close": 586.845,
      "latest_date": "2026-05-27"
    },
    "NVDA": {
      "close": 208.85,
      "latest_date": "2026-05-27"
    },
    "AVGO": {
      "close": 417.965,
      "latest_date": "2026-05-27"
    }
  },
  "signals": {
    "VRT": {
      "ratio": 9.123323,
      "ma60": 8.87006,
      "gap": 0.028553,
      "entry": true
    },
    "MRVL": {
      "ratio": 0.337721,
      "ma60": 0.28153,
      "gap": 0.199594,
      "ma60_slope_proxy": 0.041543,
      "entry": true
    }
  },
  "verdict": "✅ Entry condition met: BOTH"
}