{
  "generated_at_utc": "2026-03-09T15:01:00Z",
  "as_of": {
    "run_time_utc": "2026-03-09 15:01:00"
  },
  "data_warning": true,
  "warnings": [
    "FRED OVXCLS failed (HTTPSConnectionPool(host='fred.stlouisfed.org', port=443): Read timed out. (read timeout=20)), using cached values if available.",
    "FRED VXEWZCLS failed (HTTPSConnectionPool(host='fred.stlouisfed.org', port=443): Read timed out. (read timeout=20)), using cached values if available."
  ],
  "macro": {
    "DCOILWTICO": {
      "latest": 71.13,
      "change_5d_pct": 0.071881,
      "change_4w_bp": null,
      "latest_date": "2026-03-02"
    },
    "DCOILBRENTEU": {
      "latest": 77.24,
      "change_5d_pct": 0.07427,
      "change_4w_bp": null,
      "latest_date": "2026-03-02"
    },
    "DHHNGSP": {
      "latest": 2.99,
      "change_5d_pct": -0.044728,
      "change_4w_bp": null,
      "latest_date": "2026-03-02"
    },
    "OVXCLS": {
      "latest": 83.83,
      "change_5d_pct": 0.401839,
      "change_4w_bp": null,
      "latest_date": "2026-03-05"
    },
    "VIXCLS": {
      "latest": 29.49,
      "change_5d_pct": 0.484894,
      "change_4w_bp": null,
      "latest_date": "2026-03-06"
    },
    "BAMLH0A0HYM2": {
      "latest": 3.13,
      "change_5d_pct": 0.003205,
      "change_4w_bp": 26.0,
      "latest_date": "2026-03-06"
    },
    "BAMLC0A0CM": {
      "latest": 0.84,
      "change_5d_pct": -0.023256,
      "change_4w_bp": 8.0,
      "latest_date": "2026-03-06"
    },
    "DTWEXBGS": {
      "latest": 117.8223,
      "change_5d_pct": -0.001436,
      "change_4w_bp": null,
      "latest_date": "2026-02-27"
    },
    "NFCI": {
      "latest": -0.5236,
      "change_5d_pct": -0.06471,
      "change_4w_bp": null,
      "latest_date": "2026-02-27"
    },
    "VXEWZCLS": {
      "latest": 39.28,
      "change_5d_pct": 0.237555,
      "change_4w_bp": null,
      "latest_date": "2026-03-05"
    }
  },
  "commodity_refs": {
    "WTI": {
      "source": "CL=F",
      "close": 100.29,
      "ret5d": 0.407974
    },
    "Brent": {
      "source": "BZ=F",
      "close": 102.46,
      "ret5d": 0.317983,
      "tier": ">=90"
    },
    "HenryHub_or_NG": {
      "source": "NG=F",
      "close": 3.236,
      "ret5d": 0.093243
    },
    "Brent_WTI_spread": 2.17
  },
  "gates": {
    "RISK_OK_STRICT": false,
    "RISK_OK_SOFT": true,
    "OVX_OK": false,
    "WTI_TREND_UP": true,
    "BRENT_TREND_UP": true,
    "OIL_TREND_UP": true,
    "BRAZIL_RISK_OK": false
  },
  "prices": {
    "PBR": {
      "close": 18.425,
      "latest_date": "2026-03-09",
      "volume": 22254433.0
    },
    "OXY": {
      "close": 55.975,
      "latest_date": "2026-03-09",
      "volume": 11230305.0
    },
    "VG": {
      "close": 12.735,
      "latest_date": "2026-03-09",
      "volume": 8061464.0
    },
    "RIG": {
      "close": 6.08,
      "latest_date": "2026-03-09",
      "volume": 12425777.0
    },
    "XLE": {
      "close": 57.0,
      "latest_date": "2026-03-09",
      "volume": 27780302.0
    },
    "OIH": {
      "close": 373.33,
      "latest_date": "2026-03-09",
      "volume": 263064.0
    },
    "EWZ": {
      "close": 36.37,
      "latest_date": "2026-03-09",
      "volume": 12105527.0
    },
    "LNG": {
      "close": 257.4,
      "latest_date": "2026-03-09",
      "volume": 1489240.0
    },
    "SPY": {
      "close": 668.06,
      "latest_date": "2026-03-09",
      "volume": 27771118.0
    },
    "BRL=X": {
      "close": 5.2046,
      "latest_date": "2026-03-09",
      "volume": 0.0
    },
    "CL=F": {
      "close": 100.29,
      "latest_date": "2026-03-09",
      "volume": 690951.0
    },
    "BZ=F": {
      "close": 102.46,
      "latest_date": "2026-03-09",
      "volume": 140735.0
    },
    "NG=F": {
      "close": 3.236,
      "latest_date": "2026-03-09",
      "volume": 128346.0
    }
  },
  "signals": {
    "OXY": {
      "trend": {
        "close": 55.974998,
        "ma20": 50.64425,
        "ma60": 45.201917,
        "ma200": 43.867572,
        "gap20": 0.105259,
        "gap60": 0.238332,
        "ret5d": 0.032559,
        "high20": 55.974998,
        "low20": 45.490002
      },
      "ratio": {
        "ratio": 0.982018,
        "ma60": 0.906226,
        "gap": 0.083634,
        "slope_proxy": -0.003999
      },
      "volume": {
        "vol": 11230305.0,
        "ma20": 15512580.25,
        "ratio": 0.723948
      },
      "checks": {
        "RISK_OK_STRICT": false,
        "WTI_TREND_UP": true,
        "OXY_TREND_UP": true,
        "OXY_PULLBACK_OK": false,
        "OXY_RELATIVE_OK": false
      },
      "entry": false
    },
    "PBR": {
      "trend": {
        "close": 18.424999,
        "ma20": 16.25825,
        "ma60": 14.015917,
        "ma200": 12.776321,
        "gap20": 0.133271,
        "gap60": 0.314577,
        "ret5d": 0.063799,
        "high20": 18.424999,
        "low20": 15.02
      },
      "ratio": {
        "ratio": 0.506599,
        "ma60": 0.395969,
        "gap": 0.279391,
        "slope_proxy": 0.008646
      },
      "volume": {
        "vol": 22254433.0,
        "ma20": 24659711.65,
        "ratio": 0.902461
      },
      "checks": {
        "RISK_OK_SOFT": true,
        "BRENT_TREND_UP": true,
        "BRAZIL_RISK_OK": false,
        "PBR_TREND_OK": true,
        "PBR_PULLBACK_OK": false,
        "PBR_RELATIVE_OK": false
      },
      "entry": false
    },
    "RIG": {
      "trend": {
        "close": 6.08,
        "ma20": 6.2015,
        "ma60": 5.009667,
        "ma200": 3.78155,
        "gap20": -0.019592,
        "gap60": 0.213654,
        "ret5d": -0.0272,
        "high20": 6.54,
        "low20": 5.44
      },
      "ratio": {
        "ratio": 0.016286,
        "ma60": 0.014686,
        "gap": 0.108963,
        "slope_proxy": 0.000462
      },
      "volume": {
        "vol": 12425777.0,
        "ma20": 65875343.85,
        "ratio": 0.188626
      },
      "checks": {
        "RISK_OK_STRICT": false,
        "OIL_TREND_UP": true,
        "OIH_TREND_UP": false,
        "RIG_BREAKOUT": false,
        "RIG_VOLUME_CONFIRM": false,
        "RIG_RELATIVE_OK": true
      },
      "entry": false
    },
    "VG": {
      "trend": {
        "close": 12.735,
        "ma20": 10.26875,
        "ma60": 8.6089,
        "ma200": 11.312291,
        "gap20": 0.24017,
        "gap60": 0.479283,
        "ret5d": 0.119068,
        "high20": 12.735,
        "low20": 8.77
      },
      "ratio": {
        "ratio": 0.049476,
        "ma60": 0.040682,
        "gap": 0.216139,
        "slope_proxy": 0.003159
      },
      "volume": {
        "vol": 8061464.0,
        "ma20": 16627918.2,
        "ratio": 0.484815
      },
      "checks": {
        "RISK_OK_STRICT": false,
        "LNG_PEER_TREND_UP": true,
        "VG_TREND_UP": true,
        "VG_RELATIVE_TURN_UP": false,
        "VG_NOT_EXTENDED": false
      },
      "entry": false
    }
  },
  "verdict": "⏸ No entry today"
}