{
  "generated_at_utc": "2026-03-11T03:01:09Z",
  "as_of": {
    "price_date": "2026-03-10",
    "run_time_utc": "2026-03-11 03:01:09"
  },
  "data_warning": false,
  "warnings": [],
  "thresholds": {
    "RISK": {
      "VIX_MAX": 30.0,
      "HY_4W_CHG_BP_MAX": 150.0,
      "IG_4W_CHG_BP_MAX": 80.0,
      "REALYIELD_4W_CHG_BP_MAX": 50.0,
      "NFCI_MAX": 0.5
    },
    "REGIME": {
      "MINERS_RS_GAP_MIN": 0.0,
      "MINERS_RS_SLOPE_MIN": 0.0,
      "METALS_MA_SLOPE_LOOKBACK": 20.0
    },
    "VZLA": {
      "ATR14_PCT_MAX": 0.15,
      "GAP_OPEN_MAX": 0.08,
      "SHOCK_DOWN_RET": -0.12,
      "SHOCK_DOWN_VOL": 2.0,
      "SHOCK_UP_RET": 0.25,
      "SHOCK_UP_VOL": 3.0,
      "PULLBACK_GAP20_MIN": -0.02,
      "PULLBACK_GAP20_MAX": 0.05,
      "PULLBACK_RSI_MIN": 40.0,
      "PULLBACK_RSI_MAX": 60.0,
      "BREAKOUT_WIN": 60.0,
      "BREAKOUT_BUFFER": 1.01,
      "BREAKOUT_VOL_MIN": 2.0,
      "BREAKOUT_RSI_MIN": 60.0,
      "RS_GAP_MIN": 0.0,
      "RS_SLOPE_MIN": 0.0,
      "GAP20_OVERHEAT_MAX": 0.15
    },
    "SCZM": {
      "SILVER_WATCH": 32.0,
      "SILVER_ENTRY": 35.0,
      "ATR14_PCT_MAX": 0.2,
      "GAP_OPEN_MAX": 0.1,
      "SHOCK_DOWN_RET": -0.12,
      "SHOCK_DOWN_VOL": 2.0,
      "PULLBACK_GAP20_MIN": -0.02,
      "PULLBACK_GAP20_MAX": 0.07,
      "PULLBACK_RSI_MIN": 35.0,
      "PULLBACK_RSI_MAX": 60.0,
      "PULLBACK_VOL_MIN": 1.2,
      "BREAKOUT_WIN": 40.0,
      "BREAKOUT_BUFFER": 1.01,
      "BREAKOUT_VOL_MIN": 1.5,
      "BREAKOUT_RSI_MIN": 55.0,
      "RS_GAP_MIN": 0.0,
      "RS_SLOPE_MIN": 0.0,
      "GAP20_OVERHEAT_MAX": 0.18
    },
    "HYMC": {
      "ATR14_PCT_MAX": 0.25,
      "GAP_OPEN_MAX": 0.12,
      "SHOCK_DOWN_RET": -0.15,
      "SHOCK_DOWN_VOL": 2.5,
      "SHOCK_UP_RET": 0.3,
      "SHOCK_UP_VOL": 4.0,
      "BREAKOUT_WIN": 120.0,
      "BREAKOUT_BUFFER": 1.01,
      "BREAKOUT_VOL_MIN": 2.0,
      "BREAKOUT_VOL_MAX": 8.0,
      "BREAKOUT_RSI_MIN": 55.0,
      "RETEST_GAP50_MAX": 0.05,
      "RETEST_RSI_MIN": 50.0,
      "RS_GAP_MIN": 0.0,
      "RS_SLOPE_MIN": 0.0,
      "GAP20_OVERHEAT_MAX": 0.2
    }
  },
  "macro": {
    "BAMLH0A0HYM2": {
      "latest": 3.19,
      "change_4w": 35.0,
      "latest_date": "2026-03-09"
    },
    "BAMLC0A0CM": {
      "latest": 0.85,
      "change_4w": 9.0,
      "latest_date": "2026-03-09"
    },
    "DFII10": {
      "latest": 1.78,
      "change_4w": -9.0,
      "latest_date": "2026-03-09"
    },
    "VIXCLS": {
      "latest": 25.5,
      "change_4w": 8.14,
      "latest_date": "2026-03-09"
    },
    "NFCI": {
      "latest": -0.52365,
      "change_4w": 0.033,
      "latest_date": "2026-02-27"
    }
  },
  "risk_checks": {
    "VIX_lt_max": true,
    "HY_4w_chg_bp_lt_max": true,
    "IG_4w_chg_bp_lt_max": true,
    "RealYield_4w_chg_bp_lt_max": true,
    "NFCI_lte_max": true
  },
  "prices": {
    "VZLA": {
      "close": 4.14,
      "latest_date": "2026-03-10"
    },
    "SCZM": {
      "close": 10.62,
      "latest_date": "2026-03-10"
    },
    "HYMC": {
      "close": 44.849998,
      "latest_date": "2026-03-10"
    },
    "SI=F": {
      "close": 89.144997,
      "latest_date": "2026-03-10"
    },
    "GC=F": {
      "close": 5222.600098,
      "latest_date": "2026-03-10"
    },
    "SILJ": {
      "close": 35.41,
      "latest_date": "2026-03-10"
    },
    "SLV": {
      "close": 80.089996,
      "latest_date": "2026-03-10"
    },
    "GDXJ": {
      "close": 138.940002,
      "latest_date": "2026-03-10"
    },
    "GLD": {
      "close": 477.859985,
      "latest_date": "2026-03-10"
    }
  },
  "regime": {
    "risk_green": true,
    "silver_uptrend": true,
    "gold_uptrend": true,
    "miners_leadership": false,
    "junior_gold_leadership": false,
    "SILJ_over_SLV": {
      "ratio": 0.442128,
      "ma60": 0.441825,
      "gap": 0.000685,
      "ma60_slope_proxy": -0.002749
    },
    "GDXJ_over_GLD": {
      "ratio": 0.290755,
      "ma60": 0.295301,
      "gap": -0.015394,
      "ma60_slope_proxy": 0.012948
    },
    "metals": {
      "SI": {
        "close": 89.144997,
        "ma20": 83.2646,
        "ma50": 84.94244,
        "ma120": 65.727975,
        "ma200": 54.490655,
        "gap20": 0.070623,
        "gap50": 0.049475,
        "gap200": 0.635969,
        "ma50_slope20": 8.5997,
        "ma200_slope20": 5.06251,
        "rsi14": 54.952873,
        "atr14": 6.286686,
        "atr14_pct": 0.070522,
        "vol_ratio": 1.323347,
        "ret1d": 0.060846,
        "gap_open": 0.05323
      },
      "GC": {
        "close": 5222.600098,
        "ma20": 5097.35498,
        "ma50": 4868.485986,
        "ma120": 4406.023322,
        "ma200": 3999.485491,
        "gap20": 0.024571,
        "gap50": 0.072736,
        "gap200": 0.305818,
        "ma50_slope20": 325.403994,
        "ma200_slope20": 181.876,
        "rsi14": 58.119302,
        "atr14": 133.775938,
        "atr14_pct": 0.025615,
        "vol_ratio": 9.617318,
        "ret1d": 0.025749,
        "gap_open": 0.020132
      }
    }
  },
  "signals": {
    "VZLA": {
      "name": "Vizsla Silver",
      "ta": {
        "close": 4.14,
        "ma20": 3.988,
        "ma50": 5.0196,
        "ma120": 4.745833,
        "ma200": 4.1658,
        "gap20": 0.038114,
        "gap50": -0.175233,
        "gap200": -0.006193,
        "ma50_slope20": -0.4838,
        "ma200_slope20": 0.1701,
        "rsi14": 44.953624,
        "atr14": 0.327648,
        "atr14_pct": 0.079142,
        "vol_ratio": 0.474055,
        "ret1d": 0.037594,
        "gap_open": 0.022556
      },
      "rs_vs_SILJ": {
        "ratio": 0.116916,
        "ma60": 0.157293,
        "gap": -0.256697,
        "ma60_slope_proxy": -0.029171
      },
      "checks": {
        "trend_ok": false,
        "rs_ok": false,
        "risk_ok": true,
        "shock_down": false,
        "shock_up": false,
        "pullback": true,
        "breakout": false
      },
      "entry_candidate": false,
      "entry_confirmed": false,
      "fails": [
        "MinersLeadership(SILJ/SLV)=FALSE",
        "Trend(MA200/MA50)=FALSE",
        "RelativeStrength(vs SILJ)=FALSE"
      ]
    },
    "SCZM": {
      "name": "Santacruz Silver",
      "ta": {
        "close": 10.62,
        "ma20": 10.9295,
        "ma50": 11.491328,
        "ma120": 8.868493,
        "ma200": 6.847492,
        "gap20": -0.028318,
        "gap50": -0.075825,
        "gap200": 0.550933,
        "ma50_slope20": 0.876154,
        "ma200_slope20": 0.941636,
        "rsi14": 46.498937,
        "atr14": 1.062391,
        "atr14_pct": 0.100037,
        "vol_ratio": 0.675004,
        "ret1d": 0.051485,
        "gap_open": 0.047525
      },
      "ma_long": 200,
      "silver_margin": {
        "SI_close": 89.144997,
        "watch_ge": 32.0,
        "entry_ge": 35.0,
        "watch": true,
        "entry": true
      },
      "rs_vs_SILJ": {
        "ratio": 0.299915,
        "ma60": 0.338199,
        "gap": -0.113198,
        "ma60_slope_proxy": 0.006867
      },
      "checks": {
        "trend_ok": true,
        "rs_ok": false,
        "risk_ok": true,
        "shock_down": false,
        "pullback": false,
        "breakout": false
      },
      "entry_candidate": false,
      "entry_confirmed": false,
      "fails": [
        "MinersLeadership(SILJ/SLV)=FALSE",
        "RelativeStrength(vs SILJ)=FALSE",
        "Trigger(Pullback/Breakout)=FALSE"
      ]
    },
    "HYMC": {
      "name": "Hycroft Mining",
      "ta": {
        "close": 44.849998,
        "ma20": 42.68975,
        "ma50": 38.5267,
        "ma120": 21.680625,
        "ma200": 14.562575,
        "gap20": 0.050603,
        "gap50": 0.164128,
        "gap200": 2.079812,
        "ma50_slope20": 11.2849,
        "ma200_slope20": 3.944475,
        "rsi14": 53.416092,
        "atr14": 5.900394,
        "atr14_pct": 0.131558,
        "vol_ratio": 1.075242,
        "ret1d": 0.10468,
        "gap_open": 0.031035
      },
      "rs_vs_SILJ": {
        "ratio": 1.266591,
        "ma60": 1.039403,
        "gap": 0.218576,
        "ma60_slope_proxy": 0.247085
      },
      "rs_vs_GDXJ": {
        "ratio": 0.322801,
        "ma60": 0.262996,
        "gap": 0.227397,
        "ma60_slope_proxy": 0.064901
      },
      "checks": {
        "metals_ok": true,
        "sector_ok": false,
        "trend_ok": true,
        "rs_ok": true,
        "risk_ok": true,
        "shock_down": false,
        "shock_up": false,
        "breakout": false,
        "retest": false
      },
      "entry_candidate": false,
      "entry_confirmed": false,
      "fails": [
        "SectorLeadership(SILJ/SLV or GDXJ/GLD)=FALSE",
        "Trigger(Breakout/Retest)=FALSE"
      ]
    }
  },
  "verdict": "⏸ No entry today"
}